findhuman/__init__.py
findhuman/detector.py
findhuman-0.1.dist-info/METADATA
findhuman-0.1.dist-info/WHEEL
findhuman-0.1.dist-info/top_level.txt
findhuman-0.1.dist-info/RECORD
